jason_plugin_emoji_sentence/__init__.py
jason_plugin_emoji_sentence-0.1.5.dist-info/WHEEL
jason_plugin_emoji_sentence-0.1.5.dist-info/entry_points.txt
jason_plugin_emoji_sentence-0.1.5.dist-info/METADATA
jason_plugin_emoji_sentence-0.1.5.dist-info/RECORD
